{"cameraMode":{"drawMode":0,"name":"Shaded","section":"Shading Mode"},"sceneLighting":false,"audioPlay":false,"sceneViewState":{"m_AlwaysRefresh":false,"showFog":true,"showSkybox":false,"showFlares":true,"showImageEffects":true,"showParticleSystems":true,"showVisualEffectGraphs":true,"m_FxEnabled":true},"in2DMode":false,"pivot":{"x":0.0,"y":2.680000066757202,"z":0.0},"rotation":{"x":-0.00006986300286371261,"y":0.9735192060470581,"z":-0.00030164685449562967,"w":-0.2286609262228012},"size":0.7077822089195252,"orthographic":false}