{"cameraMode":{"drawMode":0,"name":"Shaded","section":"Shading Mode"},"sceneLighting":false,"audioPlay":false,"sceneViewState":{"m_AlwaysRefresh":false,"showFog":true,"showSkybox":false,"showFlares":true,"showImageEffects":true,"showParticleSystems":true,"showVisualEffectGraphs":true,"m_FxEnabled":true},"in2DMode":false,"pivot":{"x":0.0,"y":0.75,"z":0.0},"rotation":{"x":-0.20569854974746705,"y":-0.7936752438545227,"z":-0.42202484607696535,"w":0.38694801926612856},"size":2.598076105117798,"orthographic":false}